{ "Scope":"", "Constraint": "", "Type":"function", "Name":"reformUniCodeString", "Arguments": [ { "Name": "options", "Value": "" } ], "Description":"Reforms unicode character string with appropriate coding characters compatible for displaying.", "Params": [  ], "Comments":"", "Annotations":"", "Constructs": { "Namespace": "", "Interfaces": [  ], "Constructors": [  ], "StaticConstructors": [  ], "Fields": [  ], "Properties": [  ], "Methods": [  ], "InstanceFunctions": [ { "Scope":"", "Constraint": "", "Type":"", "Name":"instance.formatString", "Arguments": [ { "Name": "value", "Value": "" } ], "Description":"Formats string value with appropriate characters for displaying.", "Params": [  ], "Comments":"", "Annotations":"" } ], "Indexers": [  ], "Events": [  ], "Additionals": [  ], "ValueTypes": [  ], "Components": [] } }