{ "Id":"Abstraction.Core.Results.ResultObject", "Scope":"public", "Constraint":"",  "Partial":"",  "Type":"class",  "Name":"ResultObject", "Description":"ResultObject extends from Result and provides content object information in addition to error objects extended from Result abstract class.", "Comments":"", "Annotations":"", "Constructs": { "Namespace": { "Type":"Library.Parsers.Constructs.Namespace", "Name":"Abstraction.Core.Results", "Description":"", "Comments":"" }, "Interfaces": [ "Result" ], "Constructors": [ { "Type":"", "Scope":"public", "Name":"ResultObject", "Arguments": [  ], "Description":"Constructor initialization.", "Params": [  ], "Comments":"", "Annotations":"" },{ "Type":"", "Scope":"public", "Name":"ResultObject", "Arguments": [ { "Type": "Object", "Name": "contents" } ], "Description":"Constructor initialization using content object.", "Params": [  ], "Comments":"", "Annotations":"" },{ "Type":"", "Scope":"public", "Name":"ResultObject", "Arguments": [ { "Type": "Object", "Name": "contents" },{ "Type": "List<ObjectError>", "Name": "errors" },{ "Type": "string", "Name": "authorizationCode" } ], "Description":"Constructor initialization using contents, error and authorization code.", "Params": [ { "Name": "contents", "Value": "errors" } ], "Comments":"", "Annotations":"" } ], "StaticConstructors": [  ], "Fields": [  ], "Properties": [ { "Scope":"public", "Constraint": "", "Type": "Object", "Name":"contents", "Description":"Response content object.", "Comments":"", "Annotations":"" } ], "Methods": [  ], "InstanceFunctions": [  ], "Indexers": [  ], "Events": [  ], "Additionals": [  ], "ValueTypes": [  ], "Components": [] } }